master_worker_connection_manager/__init__.py
master_worker_connection_manager/connection_manager.py
master_worker_connection_manager/distributed_training.py
master_worker_connection_manager/main.py
multipal-0.1.1.dist-info/METADATA
multipal-0.1.1.dist-info/WHEEL
multipal-0.1.1.dist-info/top_level.txt
multipal-0.1.1.dist-info/RECORD
