Metadata-Version: 2.1
Name: multipal
Version: 0.1.1
Summary: A distributed computing framework for multi-machines over the network
Home-page: https://github.com/pigman13/multipal
Author: Ivan G. Aurelius
Author-email: ivan.gadingaurelius@gmail.com
License: UNKNOWN
Platform: UNKNOWN
Classifier: Development Status :: 3 - Alpha
Classifier: Intended Audience :: Developers
Classifier: License :: OSI Approved :: MIT License
Classifier: Operating System :: OS Independent
Classifier: Programming Language :: Python :: 3
Classifier: Programming Language :: Python :: 3.7
Classifier: Programming Language :: Python :: 3.8
Classifier: Programming Language :: Python :: 3.9
Requires-Python: >=3.8
Requires-Dist: tensorflow ==2.6.0
Requires-Dist: psutil ==5.8.0
Requires-Dist: tqdm ==4.62.3
Requires-Dist: numpy ==1.21.2
Requires-Dist: socket
Requires-Dist: threading
Requires-Dist: json
Requires-Dist: pickle
Provides-Extra: dev
Requires-Dist: pytest ; extra == 'dev'
Requires-Dist: flake8 ; extra == 'dev'
